{
  "lastUpdated": "2026-06-17T10:27:44.663Z",
  "totalProviders": 27,
  "workingProviders": 10,
  "failedProviders": 17,
  "uptimePercent": 37,
  "categories": [
    {
      "category": "ANIME",
      "providers": [
        {
          "provider": "AnimeKai",
          "baseUrl": "https://anikai.to",
          "status": 500,
          "responseTime": "N/A",
          "lastChecked": "2026-06-17T10:26:30.378Z",
          "category": "ANIME",
          "error": "Something went wrong. Please try again later."
        },
        {
          "provider": "AnimePahe",
          "baseUrl": "https://animepahe.si",
          "status": 500,
          "responseTime": "N/A",
          "lastChecked": "2026-06-17T10:26:30.377Z",
          "category": "ANIME",
          "error": "ECONNREFUSED"
        },
        {
          "provider": "AnimeSaturn",
          "baseUrl": "https://www.animesaturn.cx/",
          "status": 500,
          "responseTime": "N/A",
          "lastChecked": "2026-06-17T10:26:30.384Z",
          "category": "ANIME",
          "error": "Request failed with status code 403"
        },
        {
          "provider": "Gogoanime",
          "baseUrl": "https://gogoanime.by",
          "status": 500,
          "responseTime": "N/A",
          "lastChecked": "2026-06-17T10:26:30.632Z",
          "category": "ANIME",
          "error": "No results returned"
        },
        {
          "provider": "hianime",
          "baseUrl": "https://hianime.to",
          "status": 500,
          "responseTime": "N/A",
          "lastChecked": "2026-06-17T10:26:30.369Z",
          "category": "ANIME",
          "error": "Timeout"
        },
        {
          "provider": "KickAssAnime",
          "baseUrl": "https://kickass-anime.ru",
          "status": 500,
          "responseTime": "N/A",
          "lastChecked": "2026-06-17T10:26:30.379Z",
          "category": "ANIME",
          "error": "All domains failed for search"
        }
      ]
    },
    {
      "category": "MANGA",
      "providers": [
        {
          "provider": "ComicK",
          "baseUrl": "https://comick.art",
          "status": 200,
          "responseTime": "0.622s",
          "lastChecked": "2026-06-17T10:27:00.373Z",
          "category": "MANGA"
        },
        {
          "provider": "MangaDex",
          "baseUrl": "https://mangadex.org",
          "status": 200,
          "responseTime": "1.74s",
          "lastChecked": "2026-06-17T10:27:00.371Z",
          "category": "MANGA"
        },
        {
          "provider": "MangaHere",
          "baseUrl": "http://www.mangahere.cc",
          "status": 200,
          "responseTime": "0.232s",
          "lastChecked": "2026-06-17T10:27:00.374Z",
          "category": "MANGA"
        },
        {
          "provider": "MangaPill",
          "baseUrl": "https://mangapill.com",
          "status": 200,
          "responseTime": "0.588s",
          "lastChecked": "2026-06-17T10:27:00.375Z",
          "category": "MANGA"
        },
        {
          "provider": "WeebCentral",
          "baseUrl": "https://weebcentral.com",
          "status": 200,
          "responseTime": "0.323s",
          "lastChecked": "2026-06-17T10:27:00.942Z",
          "category": "MANGA"
        },
        {
          "provider": "AsuraScans",
          "baseUrl": "https://asuracomic.net",
          "status": 500,
          "responseTime": "N/A",
          "lastChecked": "2026-06-17T10:27:00.607Z",
          "category": "MANGA",
          "error": "undefined is not an object (evaluating 'dom.find(\".flex.items-center.justify-center > a\").attr(\"style\").split')"
        },
        {
          "provider": "MangaReader",
          "baseUrl": "https://mangareader.to",
          "status": 500,
          "responseTime": "N/A",
          "lastChecked": "2026-06-17T10:27:00.376Z",
          "category": "MANGA",
          "error": "Request failed with status code 522"
        }
      ]
    },
    {
      "category": "MOVIES",
      "providers": [
        {
          "provider": "DramaCool",
          "baseUrl": "https://dramacool.bg",
          "status": 500,
          "responseTime": "N/A",
          "lastChecked": "2026-06-17T10:27:20.043Z",
          "category": "MOVIES",
          "error": "ECONNREFUSED"
        },
        {
          "provider": "FlixHQ",
          "baseUrl": "https://flixhq.to",
          "status": 500,
          "responseTime": "N/A",
          "lastChecked": "2026-06-17T10:27:20.044Z",
          "category": "MOVIES",
          "error": "Request failed with status code 522"
        },
        {
          "provider": "Fmovies",
          "baseUrl": "https://ww4.fmovies.co",
          "status": 500,
          "responseTime": "N/A",
          "lastChecked": "2026-06-17T10:27:20.045Z",
          "category": "MOVIES",
          "error": "\"/fmovies-vrf?query=batman&apikey=\" cannot be parsed as a URL."
        },
        {
          "provider": "Goku",
          "baseUrl": "https://goku.sx",
          "status": 500,
          "responseTime": "N/A",
          "lastChecked": "2026-06-17T10:27:20.046Z",
          "category": "MOVIES",
          "error": "Request failed with status code 522"
        },
        {
          "provider": "HiMovies",
          "baseUrl": "https://himovies.sx",
          "status": 500,
          "responseTime": "N/A",
          "lastChecked": "2026-06-17T10:27:20.264Z",
          "category": "MOVIES",
          "error": "Request failed with status code 520"
        },
        {
          "provider": "SFlix",
          "baseUrl": "https://sflix.to",
          "status": 500,
          "responseTime": "N/A",
          "lastChecked": "2026-06-17T10:27:20.049Z",
          "category": "MOVIES",
          "error": "Request failed with status code 522"
        },
        {
          "provider": "Smashystream",
          "baseUrl": "https://embed.smashystream.com",
          "status": 500,
          "responseTime": "N/A",
          "lastChecked": "2026-06-17T10:27:20.047Z",
          "category": "MOVIES",
          "error": "Method not implemented."
        },
        {
          "provider": "Turkish123",
          "baseUrl": "https://turkish123.ac/",
          "status": 500,
          "responseTime": "N/A",
          "lastChecked": "2026-06-17T10:27:20.048Z",
          "category": "MOVIES",
          "error": "No results returned"
        }
      ]
    },
    {
      "category": "BOOKS",
      "providers": []
    },
    {
      "category": "COMICS",
      "providers": [
        {
          "provider": "GetComics",
          "baseUrl": "https://getcomics.info/",
          "status": 200,
          "responseTime": "3.59s",
          "lastChecked": "2026-06-17T10:27:39.922Z",
          "category": "COMICS"
        }
      ]
    },
    {
      "category": "LIGHT_NOVELS",
      "providers": [
        {
          "provider": "NovelUpdates",
          "baseUrl": "https://www.novelupdates.com",
          "status": 500,
          "responseTime": "N/A",
          "lastChecked": "2026-06-17T10:27:43.509Z",
          "category": "LIGHT_NOVELS",
          "error": "No results returned"
        }
      ]
    },
    {
      "category": "META",
      "providers": [
        {
          "provider": "Anilist",
          "baseUrl": "https://anilist.co",
          "status": 200,
          "responseTime": "0.266s",
          "lastChecked": "2026-06-17T10:27:44.231Z",
          "category": "META"
        },
        {
          "provider": "Myanimelist",
          "baseUrl": "https://myanimelist.net/",
          "status": 200,
          "responseTime": "0.430s",
          "lastChecked": "2026-06-17T10:27:44.233Z",
          "category": "META"
        },
        {
          "provider": "TMDB",
          "baseUrl": "https://www.themoviedb.org",
          "status": 200,
          "responseTime": "0.178s",
          "lastChecked": "2026-06-17T10:27:44.234Z",
          "category": "META"
        }
      ]
    },
    {
      "category": "NEWS",
      "providers": [
        {
          "provider": "Anime News Network",
          "baseUrl": "https://www.animenewsnetwork.com",
          "status": 200,
          "responseTime": "0.000432s",
          "lastChecked": "2026-06-17T10:27:44.663Z",
          "category": "NEWS"
        }
      ]
    }
  ]
}