{
  "lastUpdated": "2025-12-28T18:18:34.317Z",
  "totalProviders": 27,
  "workingProviders": 16,
  "failedProviders": 11,
  "uptimePercent": 59.3,
  "categories": [
    {
      "category": "ANIME",
      "providers": [
        {
          "provider": "AnimeKai",
          "baseUrl": "https://anikai.to",
          "status": 200,
          "responseTime": "0.487s",
          "lastChecked": "2025-12-28T18:18:24.429Z",
          "category": "ANIME"
        },
        {
          "provider": "AnimePahe",
          "baseUrl": "https://animepahe.si",
          "status": 200,
          "responseTime": "0.493s",
          "lastChecked": "2025-12-28T18:18:24.428Z",
          "category": "ANIME"
        },
        {
          "provider": "hianime",
          "baseUrl": "https://hianime.to",
          "status": 200,
          "responseTime": "0.590s",
          "lastChecked": "2025-12-28T18:18:24.421Z",
          "category": "ANIME"
        },
        {
          "provider": "AnimeSaturn",
          "baseUrl": "https://www.animesaturn.cx/",
          "status": 500,
          "responseTime": "N/A",
          "lastChecked": "2025-12-28T18:18:24.433Z",
          "category": "ANIME",
          "error": "Request failed with status code 403"
        },
        {
          "provider": "Gogoanime",
          "baseUrl": "https://gogoanime.by",
          "status": 500,
          "responseTime": "N/A",
          "lastChecked": "2025-12-28T18:18:24.709Z",
          "category": "ANIME",
          "error": "No results returned"
        },
        {
          "provider": "KickAssAnime",
          "baseUrl": "https://kickass-anime.ru",
          "status": 500,
          "responseTime": "N/A",
          "lastChecked": "2025-12-28T18:18:24.432Z",
          "category": "ANIME",
          "error": "All domains failed for search"
        }
      ]
    },
    {
      "category": "MANGA",
      "providers": [
        {
          "provider": "ComicK",
          "baseUrl": "https://comick.art",
          "status": 200,
          "responseTime": "1.18s",
          "lastChecked": "2025-12-28T18:18:25.617Z",
          "category": "MANGA"
        },
        {
          "provider": "MangaDex",
          "baseUrl": "https://mangadex.org",
          "status": 200,
          "responseTime": "0.524s",
          "lastChecked": "2025-12-28T18:18:25.615Z",
          "category": "MANGA"
        },
        {
          "provider": "MangaHere",
          "baseUrl": "http://www.mangahere.cc",
          "status": 200,
          "responseTime": "0.156s",
          "lastChecked": "2025-12-28T18:18:25.618Z",
          "category": "MANGA"
        },
        {
          "provider": "MangaPill",
          "baseUrl": "https://mangapill.com",
          "status": 200,
          "responseTime": "0.428s",
          "lastChecked": "2025-12-28T18:18:25.619Z",
          "category": "MANGA"
        },
        {
          "provider": "MangaReader",
          "baseUrl": "https://mangareader.to",
          "status": 200,
          "responseTime": "0.737s",
          "lastChecked": "2025-12-28T18:18:25.620Z",
          "category": "MANGA"
        },
        {
          "provider": "AsuraScans",
          "baseUrl": "https://asuracomic.net",
          "status": 500,
          "responseTime": "N/A",
          "lastChecked": "2025-12-28T18:18:25.775Z",
          "category": "MANGA",
          "error": "Request failed with status code 403"
        },
        {
          "provider": "WeebCentral",
          "baseUrl": "https://weebcentral.com",
          "status": 500,
          "responseTime": "N/A",
          "lastChecked": "2025-12-28T18:18:25.882Z",
          "category": "MANGA",
          "error": "Request failed with status code 403"
        }
      ]
    },
    {
      "category": "MOVIES",
      "providers": [
        {
          "provider": "FlixHQ",
          "baseUrl": "https://flixhq.to",
          "status": 200,
          "responseTime": "6.41s",
          "lastChecked": "2025-12-28T18:18:26.798Z",
          "category": "MOVIES"
        },
        {
          "provider": "Goku",
          "baseUrl": "https://goku.sx",
          "status": 200,
          "responseTime": "4.38s",
          "lastChecked": "2025-12-28T18:18:26.799Z",
          "category": "MOVIES"
        },
        {
          "provider": "HiMovies",
          "baseUrl": "https://himovies.sx",
          "status": 200,
          "responseTime": "0.700s",
          "lastChecked": "2025-12-28T18:18:27.212Z",
          "category": "MOVIES"
        },
        {
          "provider": "SFlix",
          "baseUrl": "https://sflix.to",
          "status": 200,
          "responseTime": "0.624s",
          "lastChecked": "2025-12-28T18:18:26.801Z",
          "category": "MOVIES"
        },
        {
          "provider": "DramaCool",
          "baseUrl": "https://dramacool.bg",
          "status": 500,
          "responseTime": "N/A",
          "lastChecked": "2025-12-28T18:18:26.797Z",
          "category": "MOVIES",
          "error": "No results returned"
        },
        {
          "provider": "Fmovies",
          "baseUrl": "https://ww4.fmovies.co",
          "status": 500,
          "responseTime": "N/A",
          "lastChecked": "2025-12-28T18:18:26.799Z",
          "category": "MOVIES",
          "error": "\"/fmovies-vrf?query=batman&apikey=\" cannot be parsed as a URL."
        },
        {
          "provider": "Smashystream",
          "baseUrl": "https://embed.smashystream.com",
          "status": 500,
          "responseTime": "N/A",
          "lastChecked": "2025-12-28T18:18:26.800Z",
          "category": "MOVIES",
          "error": "Method not implemented."
        },
        {
          "provider": "Turkish123",
          "baseUrl": "https://turkish123.ac/",
          "status": 500,
          "responseTime": "N/A",
          "lastChecked": "2025-12-28T18:18:26.800Z",
          "category": "MOVIES",
          "error": "No results returned"
        }
      ]
    },
    {
      "category": "BOOKS",
      "providers": []
    },
    {
      "category": "COMICS",
      "providers": [
        {
          "provider": "GetComics",
          "baseUrl": "https://getcomics.info/",
          "status": 500,
          "responseTime": "N/A",
          "lastChecked": "2025-12-28T18:18:33.209Z",
          "category": "COMICS",
          "error": "Request failed with status code 403"
        }
      ]
    },
    {
      "category": "LIGHT_NOVELS",
      "providers": [
        {
          "provider": "NovelUpdates",
          "baseUrl": "https://www.novelupdates.com",
          "status": 500,
          "responseTime": "N/A",
          "lastChecked": "2025-12-28T18:18:33.560Z",
          "category": "LIGHT_NOVELS",
          "error": "No results returned"
        }
      ]
    },
    {
      "category": "META",
      "providers": [
        {
          "provider": "Anilist",
          "baseUrl": "https://anilist.co",
          "status": 200,
          "responseTime": "0.120s",
          "lastChecked": "2025-12-28T18:18:33.765Z",
          "category": "META"
        },
        {
          "provider": "Myanimelist",
          "baseUrl": "https://myanimelist.net/",
          "status": 200,
          "responseTime": "0.549s",
          "lastChecked": "2025-12-28T18:18:33.767Z",
          "category": "META"
        },
        {
          "provider": "TMDB",
          "baseUrl": "https://www.themoviedb.org",
          "status": 200,
          "responseTime": "0.173s",
          "lastChecked": "2025-12-28T18:18:33.769Z",
          "category": "META"
        }
      ]
    },
    {
      "category": "NEWS",
      "providers": [
        {
          "provider": "Anime News Network",
          "baseUrl": "https://www.animenewsnetwork.com",
          "status": 200,
          "responseTime": "0.000291s",
          "lastChecked": "2025-12-28T18:18:34.316Z",
          "category": "NEWS"
        }
      ]
    }
  ]
}