{
  "lastUpdated": "2026-05-19T19:43:56.190Z",
  "totalProviders": 27,
  "workingProviders": 10,
  "failedProviders": 17,
  "uptimePercent": 37,
  "categories": [
    {
      "category": "ANIME",
      "providers": [
        {
          "provider": "AnimeKai",
          "baseUrl": "https://anikai.to",
          "status": 200,
          "responseTime": "0.426s",
          "lastChecked": "2026-05-19T19:42:44.882Z",
          "category": "ANIME"
        },
        {
          "provider": "AnimePahe",
          "baseUrl": "https://animepahe.si",
          "status": 500,
          "responseTime": "N/A",
          "lastChecked": "2026-05-19T19:42:44.878Z",
          "category": "ANIME",
          "error": "ECONNREFUSED"
        },
        {
          "provider": "AnimeSaturn",
          "baseUrl": "https://www.animesaturn.cx/",
          "status": 500,
          "responseTime": "N/A",
          "lastChecked": "2026-05-19T19:42:44.885Z",
          "category": "ANIME",
          "error": "Request failed with status code 403"
        },
        {
          "provider": "Gogoanime",
          "baseUrl": "https://gogoanime.by",
          "status": 500,
          "responseTime": "N/A",
          "lastChecked": "2026-05-19T19:42:45.120Z",
          "category": "ANIME",
          "error": "No results returned"
        },
        {
          "provider": "hianime",
          "baseUrl": "https://hianime.to",
          "status": 500,
          "responseTime": "N/A",
          "lastChecked": "2026-05-19T19:42:44.870Z",
          "category": "ANIME",
          "error": "No results returned"
        },
        {
          "provider": "KickAssAnime",
          "baseUrl": "https://kickass-anime.ru",
          "status": 500,
          "responseTime": "N/A",
          "lastChecked": "2026-05-19T19:42:44.884Z",
          "category": "ANIME",
          "error": "All domains failed for search"
        }
      ]
    },
    {
      "category": "MANGA",
      "providers": [
        {
          "provider": "ComicK",
          "baseUrl": "https://comick.art",
          "status": 200,
          "responseTime": "0.0552s",
          "lastChecked": "2026-05-19T19:43:04.597Z",
          "category": "MANGA"
        },
        {
          "provider": "MangaDex",
          "baseUrl": "https://mangadex.org",
          "status": 200,
          "responseTime": "0.785s",
          "lastChecked": "2026-05-19T19:43:04.596Z",
          "category": "MANGA"
        },
        {
          "provider": "MangaHere",
          "baseUrl": "http://www.mangahere.cc",
          "status": 200,
          "responseTime": "0.116s",
          "lastChecked": "2026-05-19T19:43:04.598Z",
          "category": "MANGA"
        },
        {
          "provider": "MangaPill",
          "baseUrl": "https://mangapill.com",
          "status": 200,
          "responseTime": "0.394s",
          "lastChecked": "2026-05-19T19:43:04.599Z",
          "category": "MANGA"
        },
        {
          "provider": "WeebCentral",
          "baseUrl": "https://weebcentral.com",
          "status": 200,
          "responseTime": "0.350s",
          "lastChecked": "2026-05-19T19:43:04.714Z",
          "category": "MANGA"
        },
        {
          "provider": "AsuraScans",
          "baseUrl": "https://asuracomic.net",
          "status": 500,
          "responseTime": "N/A",
          "lastChecked": "2026-05-19T19:43:04.652Z",
          "category": "MANGA",
          "error": "undefined is not an object (evaluating 'dom.find(\".flex.items-center.justify-center > a\").attr(\"style\").split')"
        },
        {
          "provider": "MangaReader",
          "baseUrl": "https://mangareader.to",
          "status": 500,
          "responseTime": "N/A",
          "lastChecked": "2026-05-19T19:43:04.600Z",
          "category": "MANGA",
          "error": "Request failed with status code 522"
        }
      ]
    },
    {
      "category": "MOVIES",
      "providers": [
        {
          "provider": "DramaCool",
          "baseUrl": "https://dramacool.bg",
          "status": 500,
          "responseTime": "N/A",
          "lastChecked": "2026-05-19T19:43:24.337Z",
          "category": "MOVIES",
          "error": "No results returned"
        },
        {
          "provider": "FlixHQ",
          "baseUrl": "https://flixhq.to",
          "status": 500,
          "responseTime": "N/A",
          "lastChecked": "2026-05-19T19:43:24.339Z",
          "category": "MOVIES",
          "error": "Request failed with status code 522"
        },
        {
          "provider": "Fmovies",
          "baseUrl": "https://ww4.fmovies.co",
          "status": 500,
          "responseTime": "N/A",
          "lastChecked": "2026-05-19T19:43:24.340Z",
          "category": "MOVIES",
          "error": "\"/fmovies-vrf?query=batman&apikey=\" cannot be parsed as a URL."
        },
        {
          "provider": "Goku",
          "baseUrl": "https://goku.sx",
          "status": 500,
          "responseTime": "N/A",
          "lastChecked": "2026-05-19T19:43:24.341Z",
          "category": "MOVIES",
          "error": "Request failed with status code 522"
        },
        {
          "provider": "HiMovies",
          "baseUrl": "https://himovies.sx",
          "status": 500,
          "responseTime": "N/A",
          "lastChecked": "2026-05-19T19:43:24.808Z",
          "category": "MOVIES",
          "error": "Timeout"
        },
        {
          "provider": "SFlix",
          "baseUrl": "https://sflix.to",
          "status": 500,
          "responseTime": "N/A",
          "lastChecked": "2026-05-19T19:43:24.344Z",
          "category": "MOVIES",
          "error": "Request failed with status code 522"
        },
        {
          "provider": "Smashystream",
          "baseUrl": "https://embed.smashystream.com",
          "status": 500,
          "responseTime": "N/A",
          "lastChecked": "2026-05-19T19:43:24.342Z",
          "category": "MOVIES",
          "error": "Method not implemented."
        },
        {
          "provider": "Turkish123",
          "baseUrl": "https://turkish123.ac/",
          "status": 500,
          "responseTime": "N/A",
          "lastChecked": "2026-05-19T19:43:24.343Z",
          "category": "MOVIES",
          "error": "No results returned"
        }
      ]
    },
    {
      "category": "BOOKS",
      "providers": []
    },
    {
      "category": "COMICS",
      "providers": [
        {
          "provider": "GetComics",
          "baseUrl": "https://getcomics.info/",
          "status": 500,
          "responseTime": "N/A",
          "lastChecked": "2026-05-19T19:43:54.810Z",
          "category": "COMICS",
          "error": "Request failed with status code 403"
        }
      ]
    },
    {
      "category": "LIGHT_NOVELS",
      "providers": [
        {
          "provider": "NovelUpdates",
          "baseUrl": "https://www.novelupdates.com",
          "status": 500,
          "responseTime": "N/A",
          "lastChecked": "2026-05-19T19:43:55.228Z",
          "category": "LIGHT_NOVELS",
          "error": "No results returned"
        }
      ]
    },
    {
      "category": "META",
      "providers": [
        {
          "provider": "Anilist",
          "baseUrl": "https://anilist.co",
          "status": 200,
          "responseTime": "0.109s",
          "lastChecked": "2026-05-19T19:43:55.429Z",
          "category": "META"
        },
        {
          "provider": "Myanimelist",
          "baseUrl": "https://myanimelist.net/",
          "status": 200,
          "responseTime": "0.759s",
          "lastChecked": "2026-05-19T19:43:55.431Z",
          "category": "META"
        },
        {
          "provider": "TMDB",
          "baseUrl": "https://www.themoviedb.org",
          "status": 200,
          "responseTime": "0.252s",
          "lastChecked": "2026-05-19T19:43:55.432Z",
          "category": "META"
        }
      ]
    },
    {
      "category": "NEWS",
      "providers": [
        {
          "provider": "Anime News Network",
          "baseUrl": "https://www.animenewsnetwork.com",
          "status": 200,
          "responseTime": "0.000409s",
          "lastChecked": "2026-05-19T19:43:56.190Z",
          "category": "NEWS"
        }
      ]
    }
  ]
}